{
  "images": [
    {
      "startdate": "20181023",
      "fullstartdate": "201810230700",
      "enddate": "20181024",
      "url": "/az/hprichbg/rb/LiquidNitrogen_EN-CN8621873076_1920x1080.jpg",
      "urlbase": "/az/hprichbg/rb/LiquidNitrogen_EN-CN8621873076",
      "copyright": "Liquid nitrogen for National Chemistry Week, which runs from Oct. 21-27 (© Sunny/Getty Images)",
      "copyrightlink": "http://www.bing.com/search?q=liquid+nitrogen&FORM=hpcapt&filters=HpDate:%2220181023_0700%22",
      "title": "Can you guess what this is?",
      "quiz": "/search?q=Bing+homepage+quiz&filters=WQOskey:%22HPQuiz_20181023_LiquidNitrogen%22&FORM=HPQUIZ",
      "wp": true,
      "hsh": "fdb7a08786f1e276b76e96945fac5804",
      "drk": 1,
      "top": 1,
      "bot": 1,
      "hs": []
    },
    {
      "startdate": "20181022",
      "fullstartdate": "201810220700",
      "enddate": "20181023",
      "url": "/az/hprichbg/rb/PointLesueur_EN-CN7674211601_1920x1080.jpg",
      "urlbase": "/az/hprichbg/rb/PointLesueur_EN-CN7674211601",
      "copyright": "A common wombat at Point Lesueur on Maria Island in Tasmania, Australia (© Posnov/Getty Images)",
      "copyrightlink": "http://www.bing.com/search?q=common+wombat&form=hpcapt&filters=HpDate:%2220181022_0700%22",
      "title": "Hug a wombat today",
      "quiz": "/search?q=Bing+homepage+quiz&filters=WQOskey:%22HPQuiz_20181022_PointLesueur%22&FORM=HPQUIZ",
      "wp": true,
      "hsh": "9c97cf6de26b6dddc87c75c496fd4232",
      "drk": 1,
      "top": 1,
      "bot": 1,
      "hs": []
    },
    {
      "startdate": "20181021",
      "fullstartdate": "201810210700",
      "enddate": "20181022",
      "url": "/az/hprichbg/rb/FICPlanets_EN-CN11696191570_1920x1080.jpg",
      "urlbase": "/az/hprichbg/rb/FICPlanets_EN-CN11696191570",
      "copyright": "Studio Festi performs during Festival Internacional Cervantino in Guanajuato, Mexico (© Hector Vivas/Getty Images)",
      "copyrightlink": "http://www.bing.com/search?q=Festival+Internacional+Cervantino&form=hpcapt&filters=HpDate:%2220181021_0700%22",
      "title": "Show time in Guanajuato",
      "quiz": "/search?q=Bing+homepage+quiz&filters=WQOskey:%22HPQuiz_20181021_FICPlanets%22&FORM=HPQUIZ",
      "wp": false,
      "hsh": "68913d73a572de688f5e71029c7e200c",
      "drk": 1,
      "top": 1,
      "bot": 1,
      "hs": []
    },
    {
      "startdate": "20181020",
      "fullstartdate": "201810200700",
      "enddate": "20181021",
      "url": "/az/hprichbg/rb/VallettaMalta_EN-CN11034367769_1920x1080.jpg",
      "urlbase": "/az/hprichbg/rb/VallettaMalta_EN-CN11034367769",
      "copyright": "Valletta, Malta, one of Europe’s capitals of culture for 2018 (© Adrian Malanca/Getty Images)",
      "copyrightlink": "http://www.bing.com/search?q=valletta+malta&form=hpcapt&filters=HpDate:%2220181020_0700%22",
      "title": "A European Capital of Culture",
      "quiz": "/search?q=Bing+homepage+quiz&filters=WQOskey:%22HPQuiz_20181020_VallettaMalta%22&FORM=HPQUIZ",
      "wp": true,
      "hsh": "f54557f5f6d95f92df59bc975e25979e",
      "drk": 1,
      "top": 1,
      "bot": 1,
      "hs": []
    },
    {
      "startdate": "20181019",
      "fullstartdate": "201810190700",
      "enddate": "20181020",
      "url": "/az/hprichbg/rb/WorkingHarbor_EN-CN12194027907_1920x1080.jpg",
      "urlbase": "/az/hprichbg/rb/WorkingHarbor_EN-CN12194027907",
      "copyright": "Portland, Maine (© CFW Photography/Getty Images)",
      "copyrightlink": "http://www.bing.com/search?q=portland+maine&form=hpcapt&filters=HpDate:%2220181019_0700%22",
      "title": "Harvest on the harbor",
      "quiz": "/search?q=Bing+homepage+quiz&filters=WQOskey:%22HPQuiz_20181019_WorkingHarbor%22&FORM=HPQUIZ",
      "wp": true,
      "hsh": "365df4717bfe08e7620083b5ba75f578",
      "drk": 1,
      "top": 1,
      "bot": 1,
      "hs": []
    },
    {
      "startdate": "20181018",
      "fullstartdate": "201810180700",
      "enddate": "20181019",
      "url": "/az/hprichbg/rb/MendenhalLake_EN-CN8702202262_1920x1080.jpg",
      "urlbase": "/az/hprichbg/rb/MendenhalLake_EN-CN8702202262",
      "copyright": "Icebergs on Mendenhall Lake near Juneau, Alaska (© John Hyde/age fotostock)",
      "copyrightlink": "http://www.bing.com/search?q=mendenhall+lake+alaska&form=hpcapt&filters=HpDate:%2220181018_0700%22",
      "title": "Alaska in autumn",
      "quiz": "/search?q=Bing+homepage+quiz&filters=WQOskey:%22HPQuiz_20181018_MendenhalLake%22&FORM=HPQUIZ",
      "wp": true,
      "hsh": "8c7568153cd4f6ee7ff932375b4d7493",
      "drk": 1,
      "top": 1,
      "bot": 1,
      "hs": []
    },
    {
      "startdate": "20181017",
      "fullstartdate": "201810170700",
      "enddate": "20181018",
      "url": "/az/hprichbg/rb/AZDino_EN-CN8671766086_1920x1080.jpg",
      "urlbase": "/az/hprichbg/rb/AZDino_EN-CN8671766086",
      "copyright": "Dinosaur tracks from the Jurassic period found near Tuba City, Arizona, in the Navajo Nation (© wanderluster/Getty Images)",
      "copyrightlink": "http://www.bing.com/search?q=national+fossil+day&form=hpcapt&filters=HpDate:%2220181017_0700%22",
      "title": "Dig this: It's National Fossil Day",
      "quiz": "/search?q=Bing+homepage+quiz&filters=WQOskey:%22HPQuiz_20181017_AZDino%22&FORM=HPQUIZ",
      "wp": true,
      "hsh": "79b8533db4c4d01100e9aace4a667421",
      "drk": 1,
      "top": 1,
      "bot": 1,
      "hs": []
    },
    {
      "startdate": "20181016",
      "fullstartdate": "201810160700",
      "enddate": "20181017",
      "url": "/az/hprichbg/rb/OxpeckerBoss_EN-CN6807610910_1920x1080.jpg",
      "urlbase": "/az/hprichbg/rb/OxpeckerBoss_EN-CN6807610910",
      "copyright": "An oxpecker sits on an African buffalo in Maasai Mara National Reserve, Kenya (© Susan Portnoy/Offset)",
      "copyrightlink": "http://www.bing.com/search?q=African+buffalo&form=hpcapt&filters=HpDate:%2220181016_0700%22",
      "title": "Get the memo? It's Boss's Day",
      "quiz": "/search?q=Bing+homepage+quiz&filters=WQOskey:%22HPQuiz_20181016_OxpeckerBoss%22&FORM=HPQUIZ",
      "wp": true,
      "hsh": "c77f8a837041f827cf4cc6353ca0585a",
      "drk": 1,
      "top": 1,
      "bot": 1,
      "hs": []
    }
  ],
  "tooltips": {
    "loading": "Loading...",
    "previous": "Previous image",
    "next": "Next image",
    "walle": "This image is not available to download as wallpaper.",
    "walls": "Download this image. Use of this image is restricted to wallpaper only."
  }
}